iv_params/__init__.py
iv_params/iv_params.py
iv_params-0.0.6.dist-info/LICENSE
iv_params-0.0.6.dist-info/METADATA
iv_params-0.0.6.dist-info/WHEEL
iv_params-0.0.6.dist-info/top_level.txt
iv_params-0.0.6.dist-info/RECORD
