Metadata-Version: 2.1
Name: iv-params
Version: 0.0.6
Summary: Perform ASTM E1036 extraction of photovoltaic IV parameters
Home-page: https://github.com/NREL/iv_params
Author: Michael Deceglie
Author-email: michael.deceglie@nrel.gov
License: UNKNOWN
Platform: UNKNOWN
Classifier: Programming Language :: Python :: 3
Classifier: Operating System :: OS Independent
Requires-Python: >=3.6
Requires-Dist: pandas
Requires-Dist: numpy
Requires-Dist: matplotlib
